setup.py
django_sockjs_tornado/__init__.py
django_sockjs_tornado/models.py
django_sockjs_tornado.egg-info/PKG-INFO
django_sockjs_tornado.egg-info/SOURCES.txt
django_sockjs_tornado.egg-info/dependency_links.txt
django_sockjs_tornado.egg-info/namespace_packages.txt
django_sockjs_tornado.egg-info/not-zip-safe
django_sockjs_tornado.egg-info/requires.txt
django_sockjs_tornado.egg-info/top_level.txt
django_sockjs_tornado/management/__init__.py
django_sockjs_tornado/management/commands/__init__.py
django_sockjs_tornado/management/commands/socketserver.py