Metadata-Version: 1.1
Name: django-sockjs-tornado
Version: 0.0.1
Summary: Makes it easy to run a SockJS server in Django through Tornado
Home-page: http://github.com/peterbe/django-sockjs-tornado/
Author: Peter Bengtsson
Author-email: mail@peterbe.com
License: Copyright (C) 2012 Peter Bengtsson
